ipasnmatcher/__init__.py
ipasnmatcher/exceptions.py
ipasnmatcher/ipasnmatcher.py
ipasnmatcher/utils.py
ipasnmatcher-1.0.4.dist-info/licenses/LICENSE
ipasnmatcher-1.0.4.dist-info/WHEEL
ipasnmatcher-1.0.4.dist-info/METADATA
ipasnmatcher-1.0.4.dist-info/RECORD
