Metadata-Version: 2.4
Name: ipasnmatcher
Version: 1.0.4
Summary: A Python library for verifying whether an IP address belongs to a specific ASN's announced prefixes. Includes local caching and asynchronous API support using RIPEstat data.
Author: Monazir Muhammad Doha
Author-email: Monazir Muhammad Doha <mmdoha@houndsec.net>
License-Expression: MIT
License-File: LICENSE
Classifier: Programming Language :: Python :: 3
Classifier: Operating System :: OS Independent
Requires-Dist: httpx>=0.27.0
Requires-Python: >=3.9
Project-URL: Homepage, https://github.com/itsmmdoha/ipasnmatcher
Project-URL: Issues, https://github.com/itsmmdoha/ipasnmatcher/issues
